{
  "bluetooth": {
    "DEVICE_NAME": "BigFinDCS5-E5FE",
    "PORT": 1,
    "MAC_ADDRESS": "00:06:66:89:E5:FE"
  },
  "board"  :{
    "DEFAULT_SETTLING_DELAY": 1,
    "DEFAULT_MAX_DEVIATION": 6,
    "DEFAULT_NUMBER_OF_READING": 5,
    "MAX_SETTLING_DELAY": 20,
    "MAX_MAX_DEVIATION": 100,
    "DEFAULT_BACKLIGHTING_LEVEL": 95,
    "MIN_BACKLIGHTING_LEVEL": 0,
    "MAX_BACKLIGHTING_LEVEL": 95,
    "DEFAULT_BACKLIGHTING_AUTO_MODE": false,
    "DEFAULT_BACKLIGHTING_SENSITIVITY": 0,
    "MIN_BACKLIGHTING_SENSITIVITY": 0,
    "MAX_BACKLIGHTING_SENSITIVITY": 7
  }
}